aioboto3_cm/__init__.py
aioboto3_cm/aioboto3_cm.py
aioboto3_cm/exceptions.py
aioboto3_cm-0.1.1.dist-info/licenses/LICENSE
aioboto3_cm-0.1.1.dist-info/METADATA
aioboto3_cm-0.1.1.dist-info/WHEEL
aioboto3_cm-0.1.1.dist-info/top_level.txt
aioboto3_cm-0.1.1.dist-info/RECORD
