Metadata-Version: 2.4
Name: aioboto3-cm
Version: 0.1.1
Summary: aioboto3 client manager. Manage aioboto3 sessions and clients without context managers (with statements).
Home-page: https://github.com/btemplep/aioboto3-cm
Author: Brandon Temple Paul
Author-email: btemplepgit@gmail.com
License: Apache License 2.0
Project-URL: Repository, https://github.com/btemplep/aioboto3-cm
Keywords: aio,aioboto3,aiobotocore,api,async,asyncio,aws,boto3,botocore,cache,client,cm,context,fastapi,fast,manager,session,sdk
Classifier: Development Status :: 4 - Beta
Classifier: License :: OSI Approved :: Apache Software License
Classifier: Natural Language :: English
Classifier: Operating System :: OS Independent
Classifier: Programming Language :: Python :: 3
Classifier: Programming Language :: Python :: 3 :: Only
Classifier: Programming Language :: Python :: 3.10
Classifier: Programming Language :: Python :: 3.11
Classifier: Programming Language :: Python :: 3.12
Classifier: Programming Language :: Python :: 3.13
Classifier: Programming Language :: Python :: 3.14
Classifier: Programming Language :: Python :: Implementation :: CPython
Classifier: Topic :: Software Development :: Libraries :: Python Modules
License-File: LICENSE
Requires-Dist: aioboto3
Requires-Dist: botocore
Provides-Extra: dev
Requires-Dist: build; extra == "dev"
Requires-Dist: coverage; extra == "dev"
Requires-Dist: moto[server]; extra == "dev"
Requires-Dist: nox; extra == "dev"
Requires-Dist: pytest; extra == "dev"
Requires-Dist: pytest-asyncio; extra == "dev"
Requires-Dist: pytest-cov; extra == "dev"
Requires-Dist: pytest-mock; extra == "dev"
Requires-Dist: pytz; extra == "dev"
Requires-Dist: twine; extra == "dev"
Dynamic: license-file
